fireo/__init__.py
fireo/database/__init__.py
fireo/database/database.py
fireo/database/errors.py
fireo/fields/__init__.py
fireo/fields/base_field.py
fireo/fields/boolean_field.py
fireo/fields/datetime_field.py
fireo/fields/enum_field.py
fireo/fields/errors.py
fireo/fields/field_attribute.py
fireo/fields/geo_point_field.py
fireo/fields/id_field.py
fireo/fields/list_field.py
fireo/fields/map_field.py
fireo/fields/nested_model_field.py
fireo/fields/number_field.py
fireo/fields/reference_field.py
fireo/fields/text_field.py
fireo/managers/__init__.py
fireo/managers/errors.py
fireo/managers/managers.py
fireo/models/__init__.py
fireo/models/errors.py
fireo/models/model.py
fireo/models/model_meta.py
fireo/queries/__init__.py
fireo/queries/base_query.py
fireo/queries/create_query.py
fireo/queries/delete_query.py
fireo/queries/errors.py
fireo/queries/filter_query.py
fireo/queries/get_query.py
fireo/queries/query_iterator.py
fireo/queries/query_set.py
fireo/queries/query_wrapper.py
fireo/queries/update_query.py
fireo/transaction/__init__.py
fireo/transaction/transaction.py
fireo/typedmodels/__init__.py
fireo/typedmodels/model.py
fireo/typedmodels/model_meta.py
fireo/typedmodels/resolver.py
fireo/typedmodels/utils.py
fireo/utils/__init__.py
fireo/utils/cursor.py
fireo/utils/types.py
fireo/utils/utils.py
fireo-2.2.2.dist-info/LICENSE
fireo-2.2.2.dist-info/METADATA
fireo-2.2.2.dist-info/WHEEL
fireo-2.2.2.dist-info/top_level.txt
fireo-2.2.2.dist-info/RECORD
