Metadata-Version: 2.1
Name: fireo
Version: 2.2.2
Summary: FireO ORM is specifically designed for the Google's Firestore.
Home-page: https://github.com/octabytes/FireO
Author: OctaByte
Author-email: Dev@octabyte.io
License: Apache 2.0
Keywords: Python Firestore Models ORM Google Cloud Firebase
Classifier: Development Status :: 5 - Production/Stable
Classifier: Intended Audience :: Developers
Classifier: Operating System :: OS Independent
Classifier: License :: OSI Approved :: Apache Software License
Classifier: Programming Language :: Python
Classifier: Programming Language :: Python :: 3.7
Classifier: Programming Language :: Python :: 3.8
Classifier: Programming Language :: Python :: 3.9
Classifier: Programming Language :: Python :: 3.10
Classifier: Programming Language :: Python :: 3.11
License-File: LICENSE
Requires-Dist: google-cloud-firestore<=2.12.0,==2.11.1
